.travis.yml
CHANGES.rst
LICENSE.txt
MANIFEST.in
README.rst
base.cfg
bootstrap.py
buildout-biel-internal.cfg
buildout.cfg
setup.py
sources.cfg
versions.cfg
etc/deploy.ini.in
etc/site.zcml.in
src/bst/__init__.py
src/bst.pygasus.demo.egg-info/PKG-INFO
src/bst.pygasus.demo.egg-info/SOURCES.txt
src/bst.pygasus.demo.egg-info/dependency_links.txt
src/bst.pygasus.demo.egg-info/entry_points.txt
src/bst.pygasus.demo.egg-info/namespace_packages.txt
src/bst.pygasus.demo.egg-info/not-zip-safe
src/bst.pygasus.demo.egg-info/requires.txt
src/bst.pygasus.demo.egg-info/top_level.txt
src/bst/pygasus/__init__.py
src/bst/pygasus/demo/__init__.py
src/bst/pygasus/demo/configure.zcml
src/bst/pygasus/demo/extjs.py
src/bst/pygasus/demo/handler.py
src/bst/pygasus/demo/model.py
src/bst/pygasus/demo/schema.py
src/bst/pygasus/demo/vocabularies.py
src/bst/pygasus/demo/vocabularies.zcml
src/bst/pygasus/demo/app/application.js
src/bst/pygasus/demo/app/controller/Card.js
src/bst/pygasus/demo/app/controller/Main.js
src/bst/pygasus/demo/app/resources/AllCards.json
src/bst/pygasus/demo/app/resources/css/ClearButton.css
src/bst/pygasus/demo/app/resources/css/styles.css
src/bst/pygasus/demo/app/resources/images/biel.ico
src/bst/pygasus/demo/app/view/CardView.js
src/bst/pygasus/demo/app/view/MainView.js
src/bst/pygasus/demo/locales/bb.extjs.demo.pot
src/bst/pygasus/demo/locales/de/LC_MESSAGES/bst.pygasus.demo.po
src/bst/pygasus/demo/locales/fr/LC_MESSAGES/bst.pygasus.demo.po
src/bst/pygasus/demo/tests/__init__.py
src/bst/pygasus/demo/tests/browser.py
src/bst/pygasus/demo/tests/testing.py