Metadata-Version: 1.1
Name: bst.pygasus.demo
Version: 1.0.2
Summary: Demo web application build with bst.pygausus framework
Home-page: https://github.com/bielbienne/bst.pygasus.demo
Author: Steve Aschwanden
Author-email: steve.aschwanden@biel-bienne.ch
License: ZPL 2.1
Keywords: pygasus web framework extjs
Platform: UNKNOWN
Classifier: Programming Language :: Python :: 3
Classifier: Natural Language :: English
Classifier: License :: OSI Approved :: Zope Public License
Classifier: Operating System :: OS Independent
Classifier: Development Status :: 4 - Beta
